metaevolv/__init__.py
metaevolv/abc.py
metaevolv/clonalg.py
metaevolv/de.py
metaevolv/ga.py
metaevolv/pso.py
metaevolv-0.1.5.dist-info/LICENSE
metaevolv-0.1.5.dist-info/METADATA
metaevolv-0.1.5.dist-info/WHEEL
metaevolv-0.1.5.dist-info/top_level.txt
metaevolv-0.1.5.dist-info/RECORD
